eventedpy
