Metadata-Version: 1.0
Name: eventedpy
Version: 0.1.7
Summary: Simple, tight event loop
Home-page: https://github.com/jackatbancast/eventedpy.git
Author: Jack Stephenson <jackatbancast>
Author-email: jack@bancast.net
License: UNKNOWN
Platform: UNKNOWN
